[{
  "unit_id": "tdw001", 
  "set_id": "tdw", 
  "collector_number": "001", 
  "name": "Thor", 
  "type": "character", 
  "rarity": "common", 
  "dimensions": "1x1", 
  "point_values": [
    200
  ], 
  "keywords": [
    "Asgardian", 
    "Avengers", 
    "Deity", 
    "Warrior"
  ], 
  "special_powers": [
    {
      "type": "trait", 
      "name": "ASGARDIAN ARMOR", 
      "description": "Once per game, when Thor would be dealt damage, you may instead give him an action token. If you do, Thor ignores that damage."
    }, 
    {
      "type": "attack", 
      "name": "MIGHTY MJOLNIR", 
      "description": "Give Thor a power action and make a ranged combat attack. This attack generates knock back, but this knock back path is not stopped by walls or squares of blocking terrain. Instead, destroy that terrain and knock back damage from this attack equals 1 damage plus 1 for each wall or squares of blocking terrain the character moved through."
    }
  ], 
  "unit_range": 8, 
  "targets": 1, 
  "speed_type": "wing", 
  "attack_type": "fist", 
  "defense_type": "indomitable", 
  "damage_type": "starburst", 
  "dial_size": 12, 
  "dial": [
    {
      "click_number": 1, 
      "starting_line": true, 
      "speed_power": "running_shot", 
      "speed_value": 11, 
      "attack_power": "special", 
      "attack_value": 11, 
      "defense_power": "impervious", 
      "defense_value": 17, 
      "damage_power": "leadership", 
      "damage_value": 4
    }, 
    {
      "click_number": 2, 
      "speed_power": "running_shot", 
      "speed_value": 10, 
      "attack_power": "special", 
      "attack_value": 10, 
      "defense_power": "impervious", 
      "defense_value": 18, 
      "damage_power": "leadership", 
      "damage_value": 4
    }, 
    {
      "click_number": 3, 
      "speed_power": "running_shot", 
      "speed_value": 10, 
      "attack_power": "special", 
      "attack_value": 10, 
      "defense_power": "impervious", 
      "defense_value": 17, 
      "damage_value": 3
    }, 
    {
      "click_number": 4, 
      "speed_power": "running_shot", 
      "speed_value": 8, 
      "attack_power": "energy_explosion", 
      "attack_value": 10, 
      "defense_power": "invulnerability", 
      "defense_value": 17, 
      "damage_value": 4
    }, 
    {
      "click_number": 5, 
      "speed_value": 8, 
      "attack_power": "energy_explosion", 
      "attack_value": 10, 
      "defense_power": "invulnerability", 
      "defense_value": 17, 
      "damage_value": 3
    }, 
    {
      "click_number": 6, 
      "speed_value": 8, 
      "attack_power": "energy_explosion", 
      "attack_value": 9, 
      "defense_power": "invulnerability", 
      "defense_value": 17, 
      "damage_value": 3
    }, 
    {
      "click_number": 7, 
      "speed_power": "charge", 
      "speed_value": 9, 
      "attack_power": "super_strength", 
      "attack_value": 10, 
      "defense_power": "invulnerability", 
      "defense_value": 16, 
      "damage_value": 3
    }, 
    {
      "click_number": 8, 
      "speed_power": "charge", 
      "speed_value": 8, 
      "attack_power": "super_strength", 
      "attack_value": 9, 
      "defense_power": "toughness", 
      "defense_value": 15, 
      "damage_power": "close_combat_expert", 
      "damage_value": 2
    }, 
    {
      "click_number": 9, 
      "speed_power": "charge", 
      "speed_value": 8, 
      "attack_power": "super_strength", 
      "attack_value": 9, 
      "defense_power": "toughness", 
      "defense_value": 15, 
      "damage_power": "close_combat_expert", 
      "damage_value": 3
    }, 
    {
      "click_number": 10, 
      "speed_power": "charge", 
      "speed_value": 7, 
      "attack_power": "super_strength", 
      "attack_value": 10, 
      "defense_power": "combat_reflexes", 
      "defense_value": 15, 
      "damage_power": "close_combat_expert", 
      "damage_value": 4
    }
  ]
}, {
  "unit_id": "tdw002", 
  "set_id": "tdw", 
  "collector_number": "002", 
  "name": "Einherjar", 
  "type": "character", 
  "rarity": "common", 
  "dimensions": "1x1", 
  "point_values": [
    50
  ], 
  "properties": [
    "generic"
  ], 
  "keywords": [
    "Asgardian", 
    "Warrior"
  ], 
  "special_powers": [
    {
      "type": "damage", 
      "name": "SHIELD WALL", 
      "description": "When Einherjar is adjacent to a friendly character named Einherjar, modify both their defense values by +1 if not already modified by this effect."
    }
  ], 
  "unit_range": 0, 
  "targets": 1, 
  "speed_type": "boot", 
  "attack_type": "fist", 
  "defense_type": "shield", 
  "damage_type": "starburst", 
  "dial_size": 12, 
  "dial": [
    {
      "click_number": 1, 
      "starting_line": true, 
      "speed_power": "charge", 
      "speed_value": 8, 
      "attack_value": 9, 
      "defense_power": "invulnerability", 
      "defense_value": 16, 
      "damage_power": "special", 
      "damage_value": 2
    }, 
    {
      "click_number": 2, 
      "speed_value": 8, 
      "attack_power": "blades_claws_fangs", 
      "attack_value": 10, 
      "defense_power": "toughness", 
      "defense_value": 17, 
      "damage_power": "special", 
      "damage_value": 2
    }, 
    {
      "click_number": 3, 
      "speed_power": "flurry", 
      "speed_value": 8, 
      "attack_value": 9, 
      "defense_power": "toughness", 
      "defense_value": 16, 
      "damage_power": "special", 
      "damage_value": 2
    }, 
    {
      "click_number": 4, 
      "speed_value": 7, 
      "attack_value": 9, 
      "defense_power": "willpower", 
      "defense_value": 16, 
      "damage_power": "special", 
      "damage_value": 3
    }, 
    {
      "click_number": 5, 
      "speed_power": "flurry", 
      "speed_value": 7, 
      "attack_value": 8, 
      "defense_power": "willpower", 
      "defense_value": 15, 
      "damage_power": "special", 
      "damage_value": 2
    }
  ]
}, {
  "unit_id": "tdw003a", 
  "set_id": "tdw", 
  "collector_number": "003a", 
  "name": "Dark Elf Soldier", 
  "type": "character", 
  "rarity": "common", 
  "dimensions": "1x1", 
  "point_values": [
    50
  ], 
  "properties": [
    "generic"
  ], 
  "keywords": [
    "Soldier", 
    "Svartalfheim", 
    "Warrior"
  ], 
  "special_powers": [
    {
      "type": "trait", 
      "name": "DRIVEN", 
      "description": "When Dark Elf Soldier would be dealt pushing damage, roll a d6. On a result of [d:4]-[d:6], ignore that pushing damage."
    }, 
    {
      "type": "attack", 
      "name": "MICRO BLACK HOLE BURST", 
      "description": "Dark Elf Soldier can use Incapacitate. This attack has an area of effect including all opposing characters adjacent to the target. In addition to the normal effects, all hit characters halve their speed values until your next turn.", 
      "powers": [
        "incapacitate"
      ]
    }
  ], 
  "unit_range": 6, 
  "targets": 1, 
  "speed_type": "boot", 
  "attack_type": "fist", 
  "defense_type": "shield", 
  "damage_type": "starburst", 
  "dial_size": 12, 
  "dial": [
    {
      "click_number": 1, 
      "starting_line": true, 
      "speed_power": "sidestep", 
      "speed_value": 7, 
      "attack_power": "special", 
      "attack_value": 10, 
      "defense_power": "super_senses", 
      "defense_value": 17, 
      "damage_value": 2
    }, 
    {
      "click_number": 2, 
      "speed_power": "sidestep", 
      "speed_value": 7, 
      "attack_power": "special", 
      "attack_value": 9, 
      "defense_power": "super_senses", 
      "defense_value": 16, 
      "damage_power": "enhancement", 
      "damage_value": 2
    }, 
    {
      "click_number": 3, 
      "speed_power": "sidestep", 
      "speed_value": 6, 
      "attack_power": "special", 
      "attack_value": 9, 
      "defense_power": "super_senses", 
      "defense_value": 17, 
      "damage_value": 1
    }, 
    {
      "click_number": 4, 
      "speed_value": 6, 
      "attack_value": 8, 
      "defense_power": "combat_reflexes", 
      "defense_value": 16, 
      "damage_power": "enhancement", 
      "damage_value": 2
    }, 
    {
      "click_number": 5, 
      "speed_value": 7, 
      "attack_value": 8, 
      "defense_power": "combat_reflexes", 
      "defense_value": 16, 
      "damage_value": 2
    }
  ]
}, {
  "unit_id": "tdw003b", 
  "set_id": "tdw", 
  "collector_number": "003b", 
  "name": "Dark Elf Soldier", 
  "type": "character", 
  "rarity": "common", 
  "dimensions": "1x1", 
  "point_values": [
    50
  ], 
  "properties": [
    "generic"
  ], 
  "keywords": [
    "Pilot", 
    "Svartalfheim", 
    "Warrior"
  ], 
  "special_powers": [
    {
      "type": "trait", 
      "name": "HARROW RIDER", 
      "description": "Dark Elf has [cs:wing] and can use the Ram ability. When he uses Ram, his movement may be made up of 2 direct paths."
    }
  ], 
  "unit_range": 6, 
  "targets": 1, 
  "speed_type": "boot", 
  "attack_type": "fist", 
  "defense_type": "shield", 
  "damage_type": "starburst", 
  "dial_size": 12, 
  "dial": [
    {
      "click_number": 1, 
      "starting_line": true, 
      "speed_value": 9, 
      "attack_value": 10, 
      "defense_power": "invulnerability", 
      "defense_value": 17, 
      "damage_value": 3
    }, 
    {
      "click_number": 2, 
      "speed_power": "sidestep", 
      "speed_value": 8, 
      "attack_value": 10, 
      "defense_power": "toughness", 
      "defense_value": 17, 
      "damage_value": 3
    }, 
    {
      "click_number": 3, 
      "speed_power": "sidestep", 
      "speed_value": 8, 
      "attack_value": 9, 
      "defense_power": "toughness", 
      "defense_value": 16, 
      "damage_power": "ranged_combat_expert", 
      "damage_value": 1
    }, 
    {
      "click_number": 4, 
      "speed_value": 7, 
      "attack_value": 9, 
      "defense_power": "toughness", 
      "defense_value": 16, 
      "damage_power": "ranged_combat_expert", 
      "damage_value": 1
    }
  ]
}, {
  "unit_id": "tdw004", 
  "set_id": "tdw", 
  "collector_number": "004", 
  "name": "Malekith", 
  "type": "character", 
  "rarity": "common", 
  "dimensions": "1x1", 
  "point_values": [
    350, 
    225
  ], 
  "team_abilities": [
    "mystics", 
    "power_cosmic"
  ], 
  "keywords": [
    "Cosmic", 
    "Mystical", 
    "Ruler", 
    "Svartalfheim"
  ], 
  "special_powers": [
    {
      "type": "trait", 
      "name": "THE AETHER AND I ARE ONE", 
      "description": "Characters hit by an attack from Malekith can't use defense powers until their next turn."
    }, 
    {
      "type": "defense", 
      "name": "LAST STAND", 
      "description": "Malekith can use Super Senses and Toughness.", 
      "powers": [
        "super_senses", 
        "toughness"
      ]
    }
  ], 
  "unit_range": 9, 
  "targets": 1, 
  "speed_type": "wing", 
  "attack_type": "fist", 
  "defense_type": "shield", 
  "damage_type": "starburst", 
  "dial_size": 12, 
  "dial": [
    {
      "click_number": 1, 
      "starting_line": true, 
      "speed_power": "running_shot", 
      "speed_value": 12, 
      "attack_value": 12, 
      "defense_power": "impervious", 
      "defense_value": 18, 
      "damage_power": "probability_control", 
      "damage_value": 5
    }, 
    {
      "click_number": 2, 
      "speed_value": 11, 
      "attack_power": "precision_strike", 
      "attack_value": 12, 
      "defense_power": "impervious", 
      "defense_value": 19, 
      "damage_power": "perplex", 
      "damage_value": 4
    }, 
    {
      "click_number": 3, 
      "speed_power": "hypersonic_speed", 
      "speed_value": 12, 
      "attack_power": "precision_strike", 
      "attack_value": 11, 
      "defense_power": "invincible", 
      "defense_value": 17, 
      "damage_power": "probability_control", 
      "damage_value": 3
    }, 
    {
      "click_number": 4, 
      "speed_power": "sidestep", 
      "speed_value": 10, 
      "attack_value": 11, 
      "defense_power": "invincible", 
      "defense_value": 18, 
      "damage_power": "perplex", 
      "damage_value": 4, 
      "starting_line": true
    }, 
    {
      "click_number": 5, 
      "speed_power": "sidestep", 
      "speed_value": 10, 
      "attack_value": 10, 
      "defense_power": "invincible", 
      "defense_value": 17, 
      "damage_power": "probability_control", 
      "damage_value": 3
    }, 
    {
      "click_number": 6, 
      "speed_power": "running_shot", 
      "speed_value": 9, 
      "attack_power": "precision_strike", 
      "attack_value": 11, 
      "defense_power": "invulnerability", 
      "defense_value": 17, 
      "damage_power": "perplex", 
      "damage_value": 3
    }, 
    {
      "click_number": 7, 
      "speed_power": "running_shot", 
      "speed_value": 10, 
      "attack_value": 12, 
      "defense_power": "invulnerability", 
      "defense_value": 18, 
      "damage_power": "probability_control", 
      "damage_value": 4
    }, 
    {
      "click_number": 8, 
      "speed_power": "sidestep", 
      "speed_value": 11, 
      "attack_value": 11, 
      "defense_power": "special", 
      "defense_value": 18, 
      "damage_power": "perplex", 
      "damage_value": 3
    }, 
    {
      "click_number": 9, 
      "speed_power": "sidestep", 
      "speed_value": 11, 
      "attack_value": 10, 
      "defense_power": "special", 
      "defense_value": 17, 
      "damage_power": "probability_control", 
      "damage_value": 3
    }, 
    {
      "click_number": 10, 
      "speed_power": "hypersonic_speed", 
      "speed_value": 11, 
      "attack_value": 10, 
      "defense_power": "special", 
      "defense_value": 18, 
      "damage_power": "perplex", 
      "damage_value": 4
    }
  ]
}, {
  "unit_id": "tdw005", 
  "set_id": "tdw", 
  "collector_number": "005", 
  "name": "Sif", 
  "type": "character", 
  "rarity": "common", 
  "dimensions": "1x1", 
  "point_values": [
    100
  ], 
  "keywords": [
    "Asgardian", 
    "Deity", 
    "Warrior"
  ], 
  "special_powers": [
    {
      "type": "trait", 
      "name": "MISTRESS OF THE BLADE", 
      "description": "Sif can use Invulnerability. When Sif is adajcent to a friendly character named Thor, he can use Shape Change, but only succeeds on a result of [d:6].", 
      "powers": [
        "invulnerability"
      ]
    }, 
    {
      "type": "defense", 
      "name": "MY LORD...MY LOVE", 
      "description": "Sif can use Invulnerablility. When Sif is adajcent to a friendly character named Thor, he can use Shape Change, but only succeeds on a result of [d:6]."
    }, 
    {
      "type": "damage", 
      "name": "NONE SO SHARP AS ASGARDIAN STEEL", 
      "description": "When Sif makes a close combat attack, she may target all adjacent opposing characters. If she does, the damage dealt by the attack can be divided in any way among the successfully hit targets, provided that all damage dealt is divided among them."
    }
  ], 
  "unit_range": 0, 
  "targets": 1, 
  "speed_type": "boot", 
  "attack_type": "fist", 
  "defense_type": "shield", 
  "damage_type": "starburst", 
  "dial_size": 12, 
  "dial": [
    {
      "click_number": 1, 
      "starting_line": true, 
      "speed_power": "charge", 
      "speed_value": 9, 
      "attack_power": "quake", 
      "attack_value": 10, 
      "defense_power": "special", 
      "defense_value": 17, 
      "damage_power": "empower", 
      "damage_value": 3
    }, 
    {
      "click_number": 2, 
      "speed_power": "flurry", 
      "speed_value": 9, 
      "attack_power": "quake", 
      "attack_value": 10, 
      "defense_power": "special", 
      "defense_value": 17, 
      "damage_power": "empower", 
      "damage_value": 3
    }, 
    {
      "click_number": 3, 
      "speed_power": "charge", 
      "speed_value": 8, 
      "attack_power": "precision_strike", 
      "attack_value": 10, 
      "defense_power": "toughness", 
      "defense_value": 18, 
      "damage_power": "special", 
      "damage_value": 3
    }, 
    {
      "click_number": 4, 
      "speed_power": "flurry", 
      "speed_value": 8, 
      "attack_power": "precision_strike", 
      "attack_value": 9, 
      "defense_power": "toughness", 
      "defense_value": 17, 
      "damage_power": "special", 
      "damage_value": 2
    }, 
    {
      "click_number": 5, 
      "speed_power": "charge", 
      "speed_value": 7, 
      "attack_power": "precision_strike", 
      "attack_value": 9, 
      "defense_power": "combat_reflexes", 
      "defense_value": 16, 
      "damage_power": "special", 
      "damage_value": 2
    }, 
    {
      "click_number": 6, 
      "speed_power": "leap_climb", 
      "speed_value": 7, 
      "attack_value": 10, 
      "defense_power": "combat_reflexes", 
      "defense_value": 16, 
      "damage_value": 2
    }
  ]
}, {
  "unit_id": "tdw006", 
  "set_id": "tdw", 
  "collector_number": "006", 
  "name": "Tyr", 
  "type": "character", 
  "rarity": "common", 
  "dimensions": "1x1", 
  "point_values": [
    200
  ], 
  "keywords": [
    "Asgardian", 
    "Brute", 
    "Deity", 
    "Warrior"
  ], 
  "special_powers": [
    {
      "type": "trait", 
      "name": "WAR-BRINGER", 
      "description": "At the beginning of your turn, all friendly characters within 6 squares, which are 100 points or less and have both the Asgardian and Warrior keywords can use Sidestep, and modify their damage values by +1 this turn."
    }, 
    {
      "type": "attack", 
      "name": "NONE CAN STAND AGAINST ME", 
      "description": "Tyr can use Quake. When he does, his damage value becomes 3 and is locked.", 
      "powers": [
        "quake"
      ]
    }, 
    {
      "type": "defense", 
      "name": "BATTLE IS WHERE I BELONG", 
      "description": "Tyr can use Invulnerability. When Tyr is targeted with a close combat attack, modify his defense value by +1 for each adjacent opposing character.", 
      "powers": [
        "invulnerability"
      ]
    }
  ], 
  "unit_range": 0, 
  "targets": 1, 
  "speed_type": "boot", 
  "attack_type": "fist", 
  "defense_type": "indomitable", 
  "damage_type": "starburst", 
  "dial_size": 12, 
  "dial": [
    {
      "click_number": 1, 
      "starting_line": true, 
      "speed_power": "charge", 
      "speed_value": 8, 
      "attack_value": 11, 
      "defense_power": "special", 
      "defense_value": 17, 
      "damage_power": "empower", 
      "damage_value": 4
    }, 
    {
      "click_number": 2, 
      "speed_power": "charge", 
      "speed_value": 8, 
      "attack_value": 11, 
      "defense_power": "invulnerability", 
      "defense_value": 17, 
      "damage_power": "empower", 
      "damage_value": 3
    }, 
    {
      "click_number": 3, 
      "speed_power": "sidestep", 
      "speed_value": 7, 
      "attack_power": "special", 
      "attack_value": 11, 
      "defense_power": "invulnerability", 
      "defense_value": 17, 
      "damage_value": 3
    }, 
    {
      "click_number": 4, 
      "speed_power": "sidestep", 
      "speed_value": 7, 
      "attack_power": "special", 
      "attack_value": 10, 
      "defense_power": "invulnerability", 
      "defense_value": 17, 
      "damage_value": 3
    }, 
    {
      "click_number": 5, 
      "speed_power": "sidestep", 
      "speed_value": 6, 
      "attack_power": "special", 
      "attack_value": 10, 
      "defense_power": "invulnerability", 
      "defense_value": 16, 
      "damage_value": 2
    }, 
    {
      "click_number": 6, 
      "speed_power": "flurry", 
      "speed_value": 6, 
      "attack_power": "blades_claws_fangs", 
      "attack_value": 10, 
      "defense_power": "special", 
      "defense_value": 16, 
      "damage_power": "empower", 
      "damage_value": 2
    }, 
    {
      "click_number": 7, 
      "speed_power": "flurry", 
      "speed_value": 5, 
      "attack_power": "blades_claws_fangs", 
      "attack_value": 9, 
      "defense_power": "special", 
      "defense_value": 15, 
      "damage_power": "empower", 
      "damage_value": 2
    }, 
    {
      "click_number": 8, 
      "speed_value": 5, 
      "attack_power": "blades_claws_fangs", 
      "attack_value": 8, 
      "defense_power": "invulnerability", 
      "defense_value": 16, 
      "damage_value": 2
    }
  ]
}, {
  "unit_id": "tdw007", 
  "set_id": "tdw", 
  "collector_number": "007", 
  "name": "Marauder", 
  "type": "character", 
  "rarity": "common", 
  "dimensions": "1x1", 
  "point_values": [
    75
  ], 
  "properties": [
    "generic"
  ], 
  "keywords": [
    "Brute"
  ], 
  "unit_range": 0, 
  "targets": 1, 
  "speed_type": "boot", 
  "attack_type": "fist", 
  "defense_type": "shield", 
  "damage_type": "starburst", 
  "dial_size": 12, 
  "dial": [
    {
      "click_number": 1, 
      "starting_line": true, 
      "speed_power": "charge", 
      "speed_value": 9, 
      "attack_value": 10, 
      "defense_power": "invulnerability", 
      "defense_value": 17, 
      "damage_power": "exploit_weakness", 
      "damage_value": 3
    }, 
    {
      "click_number": 2, 
      "speed_power": "charge", 
      "speed_value": 8, 
      "attack_power": "blades_claws_fangs", 
      "attack_value": 10, 
      "defense_power": "toughness", 
      "defense_value": 17, 
      "damage_value": 2
    }, 
    {
      "click_number": 3, 
      "speed_power": "sidestep", 
      "speed_value": 8, 
      "attack_value": 11, 
      "defense_power": "toughness", 
      "defense_value": 16, 
      "damage_power": "close_combat_expert", 
      "damage_value": 2
    }, 
    {
      "click_number": 4, 
      "speed_power": "sidestep", 
      "speed_value": 7, 
      "attack_power": "blades_claws_fangs", 
      "attack_value": 10, 
      "defense_power": "toughness", 
      "defense_value": 17, 
      "damage_value": 3
    }, 
    {
      "click_number": 5, 
      "speed_power": "plasticity", 
      "speed_value": 8, 
      "attack_power": "blades_claws_fangs", 
      "attack_value": 9, 
      "defense_power": "toughness", 
      "defense_value": 16, 
      "damage_power": "exploit_weakness", 
      "damage_value": 2
    }, 
    {
      "click_number": 6, 
      "speed_power": "plasticity", 
      "speed_value": 7, 
      "attack_value": 9, 
      "defense_power": "toughness", 
      "defense_value": 15, 
      "damage_power": "close_combat_expert", 
      "damage_value": 2
    }
  ]
}, {
  "unit_id": "tdw008", 
  "set_id": "tdw", 
  "collector_number": "008", 
  "name": "Kurse", 
  "type": "character", 
  "rarity": "common", 
  "dimensions": "1x1", 
  "point_values": [
    250
  ], 
  "team_abilities": [
    "power_cosmic"
  ], 
  "keywords": [
    "Brute", 
    "Monster", 
    "Svartalfheim", 
    "Warrior"
  ], 
  "special_powers": [
    {
      "type": "trait", 
      "name": "FOCUSED HATRED", 
      "description": "Kurse can use Battle Fury.", 
      "powers": [
        "battle_fury"
      ]
    }, 
    {
      "type": "trait", 
      "name": "ALGRIM REBORN", 
      "description": "If Kurse enters play through the Battlefield Promotion ability, he is KO'd if he crosses the red KO line. When a countdown click is showing, Kurse can't be moved, placed, targeted, or damaged and at the end your turn, turn this dial once to the right. If all characters friendly to Kurse are KO'd, all countdown clicks become KO clicks. This ability can't be ignored."
    }
  ], 
  "improved_movement": [
    "hindering", 
    "characters"
  ], 
  "unit_range": 0, 
  "targets": 1, 
  "speed_type": "boot", 
  "attack_type": "fist", 
  "defense_type": "shield", 
  "damage_type": "starburst", 
  "dial_size": 12, 
  "dial": [
    {
      "click_number": 1, 
      "starting_line": true, 
      "speed_power": "hypersonic_speed", 
      "speed_value": 7, 
      "attack_power": "super_strength", 
      "attack_value": 12, 
      "defense_power": "impervious", 
      "defense_value": 17, 
      "damage_value": 4
    }, 
    {
      "click_number": 2, 
      "speed_power": "charge", 
      "speed_value": 8, 
      "attack_power": "super_strength", 
      "attack_value": 11, 
      "defense_power": "impervious", 
      "defense_value": 18, 
      "damage_power": "close_combat_expert", 
      "damage_value": 4
    }, 
    {
      "click_number": 3, 
      "speed_power": "charge", 
      "speed_value": 9, 
      "attack_value": 11, 
      "defense_power": "invulnerability", 
      "defense_value": 18, 
      "damage_power": "exploit_weakness", 
      "damage_value": 4, 
      "starting_line": "red"
    }, 
    {
      "click_number": 4, 
      "speed_power": "sidestep", 
      "speed_value": 9, 
      "attack_power": "precision_strike", 
      "attack_value": 10, 
      "defense_power": "invulnerability", 
      "defense_value": 17, 
      "damage_power": "close_combat_expert", 
      "damage_value": 3
    }, 
    {
      "click_number": 5, 
      "speed_power": "sidestep", 
      "speed_value": 7, 
      "attack_power": "super_strength", 
      "attack_value": 10, 
      "defense_power": "invincible", 
      "defense_value": 18, 
      "damage_power": "exploit_weakness", 
      "damage_value": 3
    }, 
    {
      "click_number": 6, 
      "speed_power": "hypersonic_speed", 
      "speed_value": 8, 
      "attack_power": "precision_strike", 
      "attack_value": 11, 
      "defense_power": "invincible", 
      "defense_value": 17, 
      "damage_value": 4
    }, 
    {
      "click_number": 7, 
      "speed_power": "charge", 
      "speed_value": 7, 
      "attack_power": "super_strength", 
      "attack_value": 10, 
      "defense_power": "invincible", 
      "defense_value": 16, 
      "damage_power": "close_combat_expert", 
      "damage_value": 3
    }, 
    {
      "click_number": 8, 
      "speed_power": "sidestep", 
      "speed_value": 6, 
      "attack_power": "super_strength", 
      "attack_value": 11, 
      "defense_power": "invulnerability", 
      "defense_value": 17, 
      "damage_power": "exploit_weakness", 
      "damage_value": 3
    }, 
    {
      "click_number": 9, 
      "speed_power": "hypersonic_speed", 
      "speed_value": 6, 
      "attack_value": 10, 
      "defense_power": "impervious", 
      "defense_value": 16, 
      "damage_power": "exploit_weakness", 
      "damage_value": 3
    }, 
    {
      "click_number": 11, 
      "attack_value": "2", 
      "starting_line": "orange"
    }, 
    {
      "click_number": 12, 
      "attack_value": "1"
    }
  ]
}, {
  "unit_id": "tdw009", 
  "set_id": "tdw", 
  "collector_number": "009", 
  "name": "Algrim", 
  "type": "character", 
  "rarity": "rare", 
  "dimensions": "1x1", 
  "point_values": [
    125
  ], 
  "keywords": [
    "Svartalfheim", 
    "Warrior"
  ], 
  "special_powers": [
    {
      "type": "trait", 
      "name": "BATTLEFIELD PROMOTION: REBORN AS KURSE", 
      "description": "When Algrim would take 3 or more damage from an attack, you may replace him with [set:tdw] #008 Kurse on his orange starting line. When Algrim would be KO'd, roll a d6, and add the amount of damage he has just taken. On a result of 7 or more, replace him with [set:tdw] #008 Kurse on his orange starting line instead."
    }
  ], 
  "unit_range": 0, 
  "targets": 1, 
  "speed_type": "boot", 
  "attack_type": "fist", 
  "defense_type": "shield", 
  "damage_type": "starburst", 
  "dial_size": 12, 
  "dial": [
    {
      "click_number": 1, 
      "starting_line": true, 
      "speed_power": "charge", 
      "speed_value": 8, 
      "attack_value": 10, 
      "defense_power": "invulnerability", 
      "defense_value": 17, 
      "damage_power": "exploit_weakness", 
      "damage_value": 3
    }, 
    {
      "click_number": 2, 
      "speed_power": "sidestep", 
      "speed_value": 8, 
      "attack_value": 11, 
      "defense_power": "invulnerability", 
      "defense_value": 17, 
      "damage_power": "exploit_weakness", 
      "damage_value": 3
    }, 
    {
      "click_number": 3, 
      "speed_power": "charge", 
      "speed_value": 7, 
      "attack_power": "blades_claws_fangs", 
      "attack_value": 10, 
      "defense_power": "invulnerability", 
      "defense_value": 16, 
      "damage_value": 2
    }, 
    {
      "click_number": 4, 
      "speed_power": "charge", 
      "speed_value": 8, 
      "attack_power": "blades_claws_fangs", 
      "attack_value": 10, 
      "defense_power": "toughness", 
      "defense_value": 17, 
      "damage_value": 2
    }, 
    {
      "click_number": 5, 
      "speed_power": "flurry", 
      "speed_value": 8, 
      "attack_power": "blades_claws_fangs", 
      "attack_value": 9, 
      "defense_power": "toughness", 
      "defense_value": 17, 
      "damage_value": 2
    }, 
    {
      "click_number": 6, 
      "speed_power": "flurry", 
      "speed_value": 7, 
      "attack_value": 9, 
      "defense_power": "toughness", 
      "defense_value": 16, 
      "damage_power": "exploit_weakness", 
      "damage_value": 3
    }, 
    {
      "click_number": 7, 
      "speed_power": "sidestep", 
      "speed_value": 8, 
      "attack_value": 9, 
      "defense_power": "toughness", 
      "defense_value": 15, 
      "damage_power": "exploit_weakness", 
      "damage_value": 3
    }
  ]
}, {
  "unit_id": "tdw010", 
  "set_id": "tdw", 
  "collector_number": "010", 
  "name": "Heimdall", 
  "type": "character", 
  "rarity": "rare", 
  "dimensions": "1x1", 
  "point_values": [
    175
  ], 
  "keywords": [
    "Asgardian", 
    "Deity", 
    "Herald", 
    "Warrior"
  ], 
  "special_powers": [
    {
      "type": "trait", 
      "name": "FAR SIGHT", 
      "description": "Heimdall can use Super Senses.", 
      "powers": [
        "super_senses"
      ]
    }, 
    {
      "type": "attack", 
      "name": "ACTIVATE THE BIFROST", 
      "description": "Heimdall can use Telekinesis. If an opposing character moved or was placed adjacent to Heimdall since your last turn, Heimdall can use Telekinesis as a free action, but may only use it to place that opposing character.", 
      "powers": [
        "telekinesis"
      ]
    }, 
    {
      "type": "damage", 
      "name": "I SEE ALL THINGS", 
      "description": "Heimdall can use Perplex and Probability Control as if he had a range value of 8. When he does, he can use [it:hindering,characters].", 
      "powers": [
        "perplex", 
        "probability_control"
      ],
      "improved_targeting": [
        "hindering", 
        "characters"
      ]
    }
  ], 
  "unit_range": 0, 
  "targets": 1, 
  "speed_type": "boot", 
  "attack_type": "fist", 
  "defense_type": "indomitable", 
  "damage_type": "starburst", 
  "dial_size": 12, 
  "dial": [
    {
      "click_number": 1, 
      "starting_line": true, 
      "speed_power": "charge", 
      "speed_value": 9, 
      "attack_power": "blades_claws_fangs", 
      "attack_value": 11, 
      "defense_power": "invulnerability", 
      "defense_value": 17, 
      "damage_power": "special", 
      "damage_value": 3
    }, 
    {
      "click_number": 2, 
      "speed_power": "charge", 
      "speed_value": 9, 
      "attack_power": "blades_claws_fangs", 
      "attack_value": 11, 
      "defense_power": "invulnerability", 
      "defense_value": 18, 
      "damage_value": 3
    }, 
    {
      "click_number": 3, 
      "speed_value": 8, 
      "attack_power": "blades_claws_fangs", 
      "attack_value": 10, 
      "defense_power": "toughness", 
      "defense_value": 18, 
      "damage_value": 3
    }, 
    {
      "click_number": 4, 
      "speed_power": "charge", 
      "speed_value": 8, 
      "attack_power": "special", 
      "attack_value": 10, 
      "defense_power": "toughness", 
      "defense_value": 17, 
      "damage_power": "special", 
      "damage_value": 3
    }, 
    {
      "click_number": 5, 
      "speed_power": "charge", 
      "speed_value": 8, 
      "attack_power": "special", 
      "attack_value": 10, 
      "defense_power": "toughness", 
      "defense_value": 18, 
      "damage_value": 3
    }, 
    {
      "click_number": 6, 
      "speed_power": "charge", 
      "speed_value": 9, 
      "attack_power": "special", 
      "attack_value": 10, 
      "defense_power": "toughness", 
      "defense_value": 17, 
      "damage_power": "special", 
      "damage_value": 2
    }, 
    {
      "click_number": 7, 
      "speed_value": 8, 
      "attack_power": "special", 
      "attack_value": 9, 
      "defense_power": "toughness", 
      "defense_value": 16, 
      "damage_power": "special", 
      "damage_value": 2
    }
  ]
}, {
  "unit_id": "tdw011", 
  "set_id": "tdw", 
  "collector_number": "011", 
  "name": "Fandral", 
  "type": "character", 
  "rarity": "rare", 
  "dimensions": "1x1", 
  "point_values": [
    75
  ], 
  "keywords": [
    "Asgardian", 
    "Warrior", 
    "Warriors Three"
  ], 
  "special_powers": [
    {
      "type": "trait", 
      "name": "WARRIORS THREE", 
      "description": "Friendly characters with the Warriors Three keyword marked with one action token can use Sidestep.", 
      "powers": [
        "sidestep"
      ]
    }, 
    {
      "type": "attack", 
      "name": "JUST A FEINT!", 
      "description": "Fandral can use Blades/Claws/Fangs. Once per turn, if he uses it and the hit target takes less than 2 damage, another friendly characters may immediately make a close combat attack targeting the same character as a free action.", 
      "powers": [
        "blades_claws_fangs"
      ]
    }
  ], 
  "unit_range": 0, 
  "targets": 1, 
  "speed_type": "boot", 
  "attack_type": "fist", 
  "defense_type": "shield", 
  "damage_type": "starburst", 
  "dial_size": 12, 
  "dial": [
    {
      "click_number": 1, 
      "starting_line": true, 
      "speed_power": "charge", 
      "speed_value": 10, 
      "attack_power": "special", 
      "attack_value": 11, 
      "defense_power": "combat_reflexes", 
      "defense_value": 17, 
      "damage_power": "perplex", 
      "damage_value": 2
    }, 
    {
      "click_number": 2, 
      "speed_power": "charge", 
      "speed_value": 9, 
      "attack_power": "special", 
      "attack_value": 10, 
      "defense_power": "combat_reflexes", 
      "defense_value": 16, 
      "damage_value": 1
    }, 
    {
      "click_number": 3, 
      "speed_power": "flurry", 
      "speed_value": 9, 
      "attack_value": 10, 
      "defense_power": "willpower", 
      "defense_value": 16, 
      "damage_power": "exploit_weakness", 
      "damage_value": 2
    }, 
    {
      "click_number": 4, 
      "speed_power": "flurry", 
      "speed_value": 8, 
      "attack_value": 9, 
      "defense_power": "willpower", 
      "defense_value": 17, 
      "damage_power": "exploit_weakness", 
      "damage_value": 1
    }, 
    {
      "click_number": 5, 
      "speed_value": 10, 
      "attack_power": "special", 
      "attack_value": 9, 
      "defense_power": "willpower", 
      "defense_value": 16, 
      "damage_power": "exploit_weakness", 
      "damage_value": 1
    }
  ]
}, {
  "unit_id": "tdw012", 
  "set_id": "tdw", 
  "collector_number": "012", 
  "name": "Kronan Stone Man", 
  "type": "character", 
  "rarity": "rare", 
  "dimensions": "1x1", 
  "point_values": [
    100
  ], 
  "properties": [
    "generic"
  ], 
  "keywords": [
    "Brute", 
    "Monster"
  ], 
  "unit_range": 0, 
  "targets": 1, 
  "speed_type": "boot", 
  "attack_type": "fist", 
  "defense_type": "indomitable", 
  "damage_type": "giant", 
  "dial_size": 12, 
  "dial": [
    {
      "click_number": 1, 
      "starting_line": true, 
      "speed_power": "charge", 
      "speed_value": 9, 
      "attack_power": "super_strength", 
      "attack_value": 11, 
      "defense_power": "impervious", 
      "defense_value": 17, 
      "damage_power": "battle_fury", 
      "damage_value": 3
    }, 
    {
      "click_number": 2, 
      "speed_power": "sidestep", 
      "speed_value": 8, 
      "attack_power": "super_strength", 
      "attack_value": 10, 
      "defense_power": "invincible", 
      "defense_value": 17, 
      "damage_power": "battle_fury", 
      "damage_value": 3
    }, 
    {
      "click_number": 3, 
      "speed_power": "sidestep", 
      "speed_value": 9, 
      "attack_value": 10, 
      "defense_power": "invincible", 
      "defense_value": 18, 
      "damage_power": "close_combat_expert", 
      "damage_value": 2
    }, 
    {
      "click_number": 4, 
      "speed_power": "charge", 
      "speed_value": 8, 
      "attack_power": "super_strength", 
      "attack_value": 11, 
      "defense_power": "toughness", 
      "defense_value": 17, 
      "damage_power": "exploit_weakness", 
      "damage_value": 3
    }, 
    {
      "click_number": 5, 
      "speed_power": "charge", 
      "speed_value": 7, 
      "attack_power": "super_strength", 
      "attack_value": 12, 
      "defense_power": "toughness", 
      "defense_value": 17, 
      "damage_power": "exploit_weakness", 
      "damage_value": 2
    }, 
    {
      "click_number": 6, 
      "speed_value": 8, 
      "attack_value": 10, 
      "defense_power": "toughness", 
      "defense_value": 16, 
      "damage_power": "close_combat_expert", 
      "damage_value": 3
    }
  ]
}, {
  "unit_id": "tdw013", 
  "set_id": "tdw", 
  "collector_number": "013", 
  "name": "Loki", 
  "type": "character", 
  "rarity": "rare", 
  "dimensions": "1x1", 
  "point_values": [
    150
  ], 
  "keywords": [
    "Asgardian", 
    "Deity", 
    "Mystical"
  ], 
  "special_powers": [
    {
      "type": "trait", 
      "name": "IMPRISONED BY GREED...", 
      "description": "As long as Loki is on a countdown click, he can’t be moved, placed, targeted, assigned an action, or damaged, and at the beginning of your turn, you may turn his dial once to the right. If Loki is on a countdown click and no other friendly characters are on the map on non-countdown clicks, click Loki to click #4.", 
      "errata": true
    }, 
    {
      "type": "speed", 
      "name": "...FREED BY GRIEF", 
      "description": "When this power is first revealed, you may place Loki adjacent to an opposing character that has hit a character that is both friendly to Loki and 30 points or more. When you do, Loki may use Pulse Wave as a free action.", 
      "powers": [
        "pulse_wave"
      ]
    }, 
    {
      "type": "damage", 
      "name": "AFTER ALL, I AM THE GOD OF LIES", 
      "description": "Loki can use Probability Control and Shape Change. When Loki uses Shape Change and the result is [d:6], deal the attacker 1 unavoidable damage after actions resolve.", 
      "powers": [
        "probability_control", 
        "shape_change"
      ]
    }
  ], 
  "unit_range": 8, 
  "targets": 1, 
  "speed_type": "boot", 
  "attack_type": "fist", 
  "defense_type": "shield", 
  "damage_type": "starburst", 
  "dial_size": 12, 
  "dial": [
    {
      "click_number": 1, 
      "starting_line": true, 
      "attack_value": "3"
    }, 
    {
      "click_number": 2, 
      "attack_value": "2"
    }, 
    {
      "click_number": 3, 
      "attack_value": "1"
    }, 
    {
      "click_number": 4, 
      "speed_power": "special", 
      "speed_value": 9, 
      "attack_power": "penetrating_psychic_blast", 
      "attack_value": 10, 
      "defense_power": "mastermind", 
      "defense_value": 17, 
      "damage_power": "special", 
      "damage_value": 3
    }, 
    {
      "click_number": 5, 
      "speed_power": "stealth", 
      "speed_value": 8, 
      "attack_power": "penetrating_psychic_blast", 
      "attack_value": 10, 
      "defense_power": "mastermind", 
      "defense_value": 17, 
      "damage_power": "special", 
      "damage_value": 3
    }, 
    {
      "click_number": 6, 
      "speed_power": "flurry", 
      "speed_value": 10, 
      "attack_power": "precision_strike", 
      "attack_value": 11, 
      "defense_power": "super_senses", 
      "defense_value": 18, 
      "damage_power": "special", 
      "damage_value": 3
    }, 
    {
      "click_number": 7, 
      "speed_power": "flurry", 
      "speed_value": 10, 
      "attack_power": "precision_strike", 
      "attack_value": 11, 
      "defense_power": "super_senses", 
      "defense_value": 18, 
      "damage_power": "special", 
      "damage_value": 3
    }, 
    {
      "click_number": 8, 
      "speed_power": "charge", 
      "speed_value": 10, 
      "attack_power": "blades_claws_fangs", 
      "attack_value": 10, 
      "defense_power": "toughness", 
      "defense_value": 17, 
      "damage_power": "special", 
      "damage_value": 3
    }, 
    {
      "click_number": 9, 
      "speed_power": "charge", 
      "speed_value": 9, 
      "attack_power": "blades_claws_fangs", 
      "attack_value": 10, 
      "defense_power": "toughness", 
      "defense_value": 17, 
      "damage_power": "special", 
      "damage_value": 2
    }, 
    {
      "click_number": 10, 
      "speed_power": "phasing_teleport", 
      "speed_value": 9, 
      "attack_power": "penetrating_psychic_blast", 
      "attack_value": 9, 
      "defense_power": "regeneration", 
      "defense_value": 16, 
      "damage_power": "shape_change", 
      "damage_value": 2
    }, 
    {
      "click_number": 11, 
      "speed_power": "phasing_teleport", 
      "speed_value": 8, 
      "attack_power": "penetrating_psychic_blast", 
      "attack_value": 9, 
      "defense_power": "regeneration", 
      "defense_value": 15, 
      "damage_power": "shape_change", 
      "damage_value": 2
    }
  ]
}, {
  "unit_id": "tdw014", 
  "set_id": "tdw", 
  "collector_number": "014", 
  "name": "Malekith", 
  "type": "character", 
  "rarity": "rare", 
  "dimensions": "1x1", 
  "point_values": [
    150
  ], 
  "team_abilities": [
    "mystics"
  ], 
  "keywords": [
    "Mystical", 
    "Ruler", 
    "Svartalfheim"
  ], 
  "special_powers": [
    {
      "type": "trait", 
      "name": "LORD OF THE DARK ELVES", 
      "description": "Malekith can use Leadership. When he does and the result is [d:6], you may choose to not remove an action token and instead modify an adjacent friendly character's combat values by +1 until the beginning of your next turn.", 
      "powers": [
        "leadership"
      ]
    }, 
    {
      "type": "attack", 
      "name": "AETHER-ENHANCED POWER", 
      "description": "Malekith can use Penetrating/Psychic Blast and Pulse Wave.", 
      "powers": [
        "penetrating_psychic_blast", 
        "pulse_wave"
      ]
    }, 
    {
      "type": "damage", 
      "name": "ILLUSIONS AND DECEPTION", 
      "description": "Malekith can use Perplex and Shape Change. When he uses Shape Change and succeeds, place a Deceived token on the attacker's character card. Malekith may use Mind Control as a free action targeting any number of characters marked with Deceived tokens. Remove all Deceived tokens from characters hit by this use of Mind Control.", 
      "powers": [
        "perplex", 
        "shape_change", 
        "mind_control"
      ]
    }
  ], 
  "unit_range": 7, 
  "targets": 1, 
  "speed_type": "boot", 
  "attack_type": "fist", 
  "defense_type": "shield", 
  "damage_type": "starburst", 
  "dial_size": 12, 
  "dial": [
    {
      "click_number": 1, 
      "starting_line": true, 
      "speed_power": "stealth", 
      "speed_value": 8, 
      "attack_power": "precision_strike", 
      "attack_value": 11, 
      "defense_power": "mastermind", 
      "defense_value": 17, 
      "damage_power": "special", 
      "damage_value": 3
    }, 
    {
      "click_number": 2, 
      "speed_power": "stealth", 
      "speed_value": 7, 
      "attack_power": "precision_strike", 
      "attack_value": 10, 
      "defense_power": "mastermind", 
      "defense_value": 17, 
      "damage_power": "special", 
      "damage_value": 2
    }, 
    {
      "click_number": 3, 
      "speed_power": "stealth", 
      "speed_value": 8, 
      "attack_power": "precision_strike", 
      "attack_value": 10, 
      "defense_power": "mastermind", 
      "defense_value": 17, 
      "damage_power": "perplex", 
      "damage_value": 3
    }, 
    {
      "click_number": 4, 
      "speed_power": "stealth", 
      "speed_value": 7, 
      "attack_value": 9, 
      "defense_power": "toughness", 
      "defense_value": 17, 
      "damage_power": "perplex", 
      "damage_value": 2
    }, 
    {
      "click_number": 5, 
      "speed_power": "phasing_teleport", 
      "speed_value": 10, 
      "attack_power": "special", 
      "attack_value": 9, 
      "defense_power": "toughness", 
      "defense_value": 17, 
      "damage_power": "perplex", 
      "damage_value": 3
    }, 
    {
      "click_number": 6, 
      "speed_power": "phasing_teleport", 
      "speed_value": 9, 
      "attack_power": "special", 
      "attack_value": 10, 
      "defense_power": "toughness", 
      "defense_value": 17, 
      "damage_value": 2
    }, 
    {
      "click_number": 7, 
      "speed_power": "phasing_teleport", 
      "speed_value": 8, 
      "attack_power": "special", 
      "attack_value": 10, 
      "defense_value": 17, 
      "damage_value": 2
    }
  ]
}, {
  "unit_id": "tdw015", 
  "set_id": "tdw", 
  "collector_number": "015", 
  "name": "Duhg", 
  "type": "character", 
  "rarity": "rare", 
  "dimensions": "1x1", 
  "point_values": [
    125
  ], 
  "keywords": [
    "Armor", 
    "Brute", 
    "Duhg's Army", 
    "Monster", 
    "Soldier", 
    "Warrior"
  ], 
  "keyword_source": [
    {
      "recipient": "unit", 
      "phase": "force_construction", 
      "keywords": [
        "Duhg's Army"
      ], 
      "conditions": {
        "point_limit": 124,
        "keywords": [
          "Armor", 
          "Brute", 
          "Monster", 
          "Soldier", 
          "Warrior"
        ]
      }
    }
  ], 
  "special_powers": [
    {
      "type": "trait", 
      "name": "A MOTLEY ARMY FROM ALL NINE REALMS", 
      "description": "When building your force, if Duhg is the highest-point character, other characters that share a keyword with him also have the Duhg's Army keyword."
    }, 
    {
      "type": "defense", 
      "name": "GATHERING THE MARAUDERS", 
      "description": "Duhg can use Invulnerability and Mastermind.", 
      "powers": [
        "invulnerability", 
        "mastermind"
      ]
    }
  ], 
  "unit_range": 0, 
  "targets": 1, 
  "speed_type": "boot", 
  "attack_type": "fist", 
  "defense_type": "indomitable", 
  "damage_type": "starburst", 
  "dial_size": 12, 
  "dial": [
    {
      "click_number": 1, 
      "starting_line": true, 
      "speed_power": "charge", 
      "speed_value": 7, 
      "attack_power": "precision_strike", 
      "attack_value": 11, 
      "defense_power": "special", 
      "defense_value": 17, 
      "damage_power": "leadership", 
      "damage_value": 3
    }, 
    {
      "click_number": 2, 
      "speed_power": "sidestep", 
      "speed_value": 6, 
      "attack_power": "precision_strike", 
      "attack_value": 10, 
      "defense_power": "special", 
      "defense_value": 17, 
      "damage_power": "leadership", 
      "damage_value": 3
    }, 
    {
      "click_number": 3, 
      "speed_power": "flurry", 
      "speed_value": 7, 
      "attack_power": "blades_claws_fangs", 
      "attack_value": 10, 
      "defense_power": "invulnerability", 
      "defense_value": 17, 
      "damage_power": "perplex", 
      "damage_value": 2
    }, 
    {
      "click_number": 4, 
      "speed_power": "flurry", 
      "speed_value": 6, 
      "attack_power": "precision_strike", 
      "attack_value": 11, 
      "defense_power": "invulnerability", 
      "defense_value": 16, 
      "damage_power": "perplex", 
      "damage_value": 3
    }, 
    {
      "click_number": 5, 
      "speed_power": "charge", 
      "speed_value": 8, 
      "attack_power": "precision_strike", 
      "attack_value": 10, 
      "defense_power": "toughness", 
      "defense_value": 18, 
      "damage_power": "exploit_weakness", 
      "damage_value": 4
    }, 
    {
      "click_number": 6, 
      "speed_power": "sidestep", 
      "speed_value": 7, 
      "attack_power": "blades_claws_fangs", 
      "attack_value": 10, 
      "defense_power": "toughness", 
      "defense_value": 17, 
      "damage_power": "exploit_weakness", 
      "damage_value": 3
    }, 
    {
      "click_number": 7, 
      "speed_power": "sidestep", 
      "speed_value": 8, 
      "attack_power": "blades_claws_fangs", 
      "attack_value": 10, 
      "defense_power": "regeneration", 
      "defense_value": 16, 
      "damage_value": 2
    }
  ]
}, {
  "unit_id": "tdw016", 
  "set_id": "tdw", 
  "collector_number": "016", 
  "name": "Hogun", 
  "type": "character", 
  "rarity": "rare", 
  "dimensions": "1x1", 
  "point_values": [
    100
  ], 
  "keywords": [
    "Asgardian", 
    "Warrior", 
    "Warriors Three"
  ], 
  "special_powers": [
    {
      "type": "trait", 
      "name": "THE WARRIORS THREE", 
      "description": "Friendly characters with the Warriors Three keyword can use Empower, but only to affect characters with the Warriors Three keyword.", 
      "powers": [
        "empower"
      ]
    }, 
    {
      "type": "attack", 
      "name": "MASTER OF ALL WEAPONRY", 
      "description": "Hogun can use Super Strength but can't pick up or hold heavy or special objects. When he makes a close combat attack while holding an object, roll a d6. On a result of [d:1] through [d:3], he can use Precision Strike. On a result of [d:4] through [d:6], the object is not removed after the attack and Hogun continues to hold it.", 
      "powers": [
        "super_strength"
      ]
    }, 
    {
      "type": "defense", 
      "name": "BATTLEFIELD MEDICINE", 
      "description": "Hogun can use Regeneration and Support.", 
      "powers": [
        "regeneration", 
        "support"
      ]
    }
  ], 
  "unit_range": 0, 
  "targets": 1, 
  "speed_type": "boot", 
  "attack_type": "fist", 
  "defense_type": "shield", 
  "damage_type": "starburst", 
  "dial_size": 12, 
  "dial": [
    {
      "click_number": 1, 
      "starting_line": true, 
      "speed_power": "charge", 
      "speed_value": 8, 
      "attack_power": "special", 
      "attack_value": 11, 
      "defense_power": "invulnerability", 
      "defense_value": 17, 
      "damage_power": "outwit", 
      "damage_value": 3
    }, 
    {
      "click_number": 2, 
      "speed_power": "charge", 
      "speed_value": 8, 
      "attack_power": "special", 
      "attack_value": 10, 
      "defense_power": "invulnerability", 
      "defense_value": 17, 
      "damage_power": "outwit", 
      "damage_value": 2
    }, 
    {
      "click_number": 3, 
      "speed_value": 7, 
      "attack_power": "special", 
      "attack_value": 10, 
      "defense_power": "toughness", 
      "defense_value": 17, 
      "damage_power": "outwit", 
      "damage_value": 3
    }, 
    {
      "click_number": 4, 
      "speed_value": 7, 
      "attack_value": 9, 
      "defense_power": "toughness", 
      "defense_value": 16, 
      "damage_power": "close_combat_expert", 
      "damage_value": 2
    }, 
    {
      "click_number": 5, 
      "speed_value": 7, 
      "attack_value": 9, 
      "defense_power": "special", 
      "defense_value": 17, 
      "damage_power": "close_combat_expert", 
      "damage_value": 1
    }, 
    {
      "click_number": 6, 
      "speed_value": 8, 
      "attack_value": 10, 
      "defense_power": "special", 
      "defense_value": 17, 
      "damage_power": "close_combat_expert", 
      "damage_value": 1
    }
  ]
}, {
  "unit_id": "tdw017", 
  "set_id": "tdw", 
  "collector_number": "017", 
  "name": "Volstagg", 
  "type": "character", 
  "rarity": "rare", 
  "dimensions": "1x1", 
  "point_values": [
    125
  ], 
  "keywords": [
    "Asgardian", 
    "Warrior", 
    "Warriors Three"
  ], 
  "special_powers": [
    {
      "type": "trait", 
      "name": "THE WARRIORS THREE", 
      "description": "Friendly characters with the Warriors Three keyword can use Mastermind. When they do, they may only transfer damage to other characters with the Warriors Three keyword, but they may do so regardless of their point values.", 
      "powers": [
        "mastermind"
      ]
    }, 
    {
      "type": "attack", 
      "name": "ONE LAST FEAST WITH FRIENDS", 
      "description": "Once per game, give Volstagg a double power action that deals no pushing damage. Heal all adjacent friendly characters of damage equal to 2 minus the number of action tokens they have and, when Volstagg next clears action tokens, heal him to click #4. Other friendly characters with the Warriors Three keyword are considered adjacent during this action."
    }, 
    {
      "type": "defense", 
      "name": "TRUE LION OF ASGARD", 
      "description": "Volstagg can use Defend and Invulnerability.", 
      "powers": [
        "defend", 
        "invulnerability"
      ]
    }
  ], 
  "unit_range": 0, 
  "targets": 1, 
  "speed_type": "boot", 
  "attack_type": "fist", 
  "defense_type": "shield", 
  "damage_type": "starburst", 
  "dial_size": 12, 
  "dial": [
    {
      "click_number": 1, 
      "starting_line": true, 
      "speed_power": "plasticity", 
      "speed_value": 7, 
      "attack_value": 10, 
      "defense_power": "special", 
      "defense_value": 18, 
      "damage_power": "close_combat_expert", 
      "damage_value": 3
    }, 
    {
      "click_number": 2, 
      "speed_power": "plasticity", 
      "speed_value": 6, 
      "attack_value": 9, 
      "defense_power": "invincible", 
      "defense_value": 17, 
      "damage_power": "close_combat_expert", 
      "damage_value": 3
    }, 
    {
      "click_number": 3, 
      "speed_power": "charge", 
      "speed_value": 6, 
      "attack_value": 10, 
      "defense_power": "invincible", 
      "defense_value": 17, 
      "damage_value": 3
    }, 
    {
      "click_number": 4, 
      "speed_power": "charge", 
      "speed_value": 5, 
      "attack_value": 9, 
      "defense_power": "special", 
      "defense_value": 17, 
      "damage_value": 2
    }, 
    {
      "click_number": 5, 
      "speed_power": "force_blast", 
      "speed_value": 5, 
      "attack_value": 9, 
      "defense_power": "invulnerability", 
      "defense_value": 17, 
      "damage_value": 2
    }, 
    {
      "click_number": 6, 
      "speed_power": "force_blast", 
      "speed_value": 5, 
      "attack_power": "special", 
      "attack_value": 8, 
      "defense_power": "toughness", 
      "defense_value": 16, 
      "damage_value": 2
    }, 
    {
      "click_number": 7, 
      "speed_power": "force_blast", 
      "speed_value": 8, 
      "attack_power": "special", 
      "attack_value": 8, 
      "defense_power": "toughness", 
      "defense_value": 16, 
      "damage_value": 2
    }
  ]
}, {
  "unit_id": "tdw018", 
  "set_id": "tdw", 
  "collector_number": "018", 
  "name": "Thor", 
  "type": "character", 
  "rarity": "rare", 
  "dimensions": "1x1", 
  "point_values": [
    125
  ], 
  "keywords": [
    "Asgardian", 
    "Avengers", 
    "Deity", 
    "Warrior"
  ], 
  "special_powers": [
    {
      "type": "trait", 
      "name": "STRONGEST OF THE ASGARDIANS", 
      "description": "Thor can use Super Strength. Give Thor a close combat action and, if he hits, you may roll a d6. If the result is greater than the damage taken, replace him with [set:tdw] #001 Thor on the same click number +1.", 
      "powers": [
        "super_strength"
      ]
    }, 
    {
      "type": "trait", 
      "name": "GODLY STAMINA", 
      "description": "Thor begins the game with two Stamina tokens on his card. When Thor would take pushing damage, you may instead remove a Stamina token and ignore the pushing damage."
    }, 
    {
      "type": "attack", 
      "name": "MIGHTY SWING", 
      "description": "Thor can use Precision Strike and Quake.", 
      "powers": [
        "precision_strike", 
        "quake"
      ]
    }
  ], 
  "unit_range": 0, 
  "targets": 1, 
  "speed_type": "wing", 
  "attack_type": "fist", 
  "defense_type": "shield", 
  "damage_type": "starburst", 
  "dial_size": 12, 
  "dial": [
    {
      "click_number": 1, 
      "starting_line": true, 
      "speed_power": "charge", 
      "speed_value": 9, 
      "attack_power": "special", 
      "attack_value": 10, 
      "defense_power": "invulnerability", 
      "defense_value": 18, 
      "damage_value": 4
    }, 
    {
      "click_number": 2, 
      "speed_power": "charge", 
      "speed_value": 8, 
      "attack_power": "special", 
      "attack_value": 10, 
      "defense_power": "invulnerability", 
      "defense_value": 17, 
      "damage_value": 3
    }, 
    {
      "click_number": 3, 
      "speed_value": 8, 
      "attack_power": "special", 
      "attack_value": 9, 
      "defense_power": "invulnerability", 
      "defense_value": 17, 
      "damage_value": 3
    }, 
    {
      "click_number": 4, 
      "speed_value": 6, 
      "attack_value": 11, 
      "defense_power": "toughness", 
      "defense_value": 15, 
      "damage_power": "battle_fury", 
      "damage_value": 4
    }, 
    {
      "click_number": 5, 
      "speed_power": "flurry", 
      "speed_value": 5, 
      "attack_value": 11, 
      "defense_power": "toughness", 
      "defense_value": 15, 
      "damage_power": "battle_fury", 
      "damage_value": 4
    }, 
    {
      "click_number": 6, 
      "speed_power": "flurry", 
      "speed_value": 5, 
      "attack_value": 10, 
      "defense_power": "toughness", 
      "defense_value": 16, 
      "damage_power": "exploit_weakness", 
      "damage_value": 3
    }, 
    {
      "click_number": 7, 
      "speed_power": "charge", 
      "speed_value": 6, 
      "attack_value": 9, 
      "defense_power": "toughness", 
      "defense_value": 16, 
      "damage_power": "exploit_weakness", 
      "damage_value": 2
    }
  ]
}, {
  "unit_id": "tdw019", 
  "set_id": "tdw", 
  "collector_number": "019", 
  "name": "Thor", 
  "type": "character", 
  "rarity": "chase", 
  "dimensions": "1x1", 
  "point_values": [
    400, 
    200
  ], 
  "team_abilities": [
    "avengers_initiative"
  ], 
  "keywords": [
    "Asgardian", 
    "Avengers", 
    "Deity", 
    "Warrior"
  ], 
  "special_powers": [
    {
      "type": "trait", 
      "name": "DEFENDER OF THE NINE REALMS", 
      "description": "Thor can use Super Strength and adjacent friendly characters can use Toughness. Once per turn, Thor can use Defend.", 
      "powers": [
        "super_strength", 
        "defend"
      ]
    }, 
    {
      "type": "speed", 
      "name": "ASGARDIAN FURY", 
      "description": "Thor can use Charge and Flurry.", 
      "powers": [
        "charge", 
        "flurry"
      ]
    }, 
    {
      "type": "attack", 
      "name": "CALL DOWN THE LIGHTNING", 
      "description": "Give Thor a ranged combat action and he can use [it:characters] for this action. The area of effect for this ranged attack is any one square within range and line of fire and each square adjacent to it. A hit character occupying the chosen square is dealt Thor's printed damage value. Other hit characters are dealt Thor's printed damage -1.",
      "improved_targeting": [
        "characters"
      ]
    }
  ], 
  "improved_movement": [
    "characters"
  ], 
  "unit_range": 8, 
  "targets": 2, 
  "speed_type": "wing", 
  "attack_type": "fist", 
  "defense_type": "indomitable", 
  "damage_type": "starburst", 
  "dial_size": 12, 
  "dial": [
    {
      "click_number": 1, 
      "starting_line": true, 
      "speed_power": "running_shot", 
      "speed_value": 11, 
      "attack_power": "special", 
      "attack_value": 12, 
      "defense_power": "impervious", 
      "defense_value": 19, 
      "damage_power": "leadership", 
      "damage_value": 5
    }, 
    {
      "click_number": 2, 
      "speed_power": "special", 
      "speed_value": 11, 
      "attack_value": 11, 
      "defense_power": "invincible", 
      "defense_value": 19, 
      "damage_power": "leadership", 
      "damage_value": 4
    }, 
    {
      "click_number": 3, 
      "speed_power": "hypersonic_speed", 
      "speed_value": 10, 
      "attack_power": "special", 
      "attack_value": 10, 
      "defense_power": "impervious", 
      "defense_value": 18, 
      "damage_power": "close_combat_expert", 
      "damage_value": 4
    }, 
    {
      "click_number": 4, 
      "speed_value": 10, 
      "attack_power": "special", 
      "attack_value": 11, 
      "defense_power": "invulnerability", 
      "defense_value": 18, 
      "damage_value": 3
    }, 
    {
      "click_number": 5, 
      "speed_power": "special", 
      "speed_value": 10, 
      "attack_value": 11, 
      "defense_power": "invincible", 
      "defense_value": 18, 
      "damage_value": 4, 
      "starting_line": true
    }, 
    {
      "click_number": 6, 
      "speed_power": "hypersonic_speed", 
      "speed_value": 9, 
      "attack_value": 11, 
      "defense_power": "invulnerability", 
      "defense_value": 17, 
      "damage_value": 4
    }, 
    {
      "click_number": 7, 
      "speed_power": "hypersonic_speed", 
      "speed_value": 9, 
      "attack_value": 10, 
      "defense_power": "impervious", 
      "defense_value": 17, 
      "damage_power": "close_combat_expert", 
      "damage_value": 3
    }, 
    {
      "click_number": 8, 
      "speed_value": 9, 
      "attack_power": "special", 
      "attack_value": 10, 
      "defense_power": "invulnerability", 
      "defense_value": 16, 
      "damage_power": "close_combat_expert", 
      "damage_value": 3
    }, 
    {
      "click_number": 9, 
      "speed_power": "special", 
      "speed_value": 8, 
      "attack_power": "special", 
      "attack_value": 9, 
      "defense_power": "invulnerability", 
      "defense_value": 16, 
      "damage_value": 4
    }, 
    {
      "click_number": 10, 
      "speed_power": "running_shot", 
      "speed_value": 8, 
      "attack_power": "special", 
      "attack_value": 9, 
      "defense_power": "invulnerability", 
      "defense_value": 17, 
      "damage_value": 4
    }
  ]
}, {
  "unit_id": "tdw020", 
  "set_id": "tdw", 
  "collector_number": "020", 
  "name": "Odin", 
  "type": "character", 
  "rarity": "chase", 
  "dimensions": "1x1", 
  "point_values": [
    350, 
    200
  ], 
  "team_abilities": [
    "power_cosmic"
  ], 
  "keywords": [
    "Asgardian", 
    "Cosmic", 
    "Deity", 
    "Ruler"
  ], 
  "special_powers": [
    {
      "type": "trait", 
      "name": "GUNGNIR", 
      "description": "Once per game, give Odin a double power action and make a ranged combat attack targeting the highest-point opposing character anywhere on the map. For this attack, Odin's combat values are locked, the attack can't be evaded and the attack roll can't be rerolled by friendly characters. After actions resolve, deal Odin 1 unavoidable damage."
    }
  ], 
  "improved_targeting": [
    "hindering"
  ], 
  "unit_range": 9, 
  "targets": 2, 
  "speed_type": "wing", 
  "attack_type": "fist", 
  "defense_type": "shield", 
  "damage_type": "starburst", 
  "dial_size": 12, 
  "dial": [
    {
      "click_number": 1, 
      "starting_line": true, 
      "speed_power": "running_shot", 
      "speed_value": 12, 
      "attack_power": "penetrating_psychic_blast", 
      "attack_value": 12, 
      "defense_power": "invincible", 
      "defense_value": 19, 
      "damage_power": "leadership", 
      "damage_value": 5
    }, 
    {
      "click_number": 2, 
      "speed_power": "running_shot", 
      "speed_value": 10, 
      "attack_power": "penetrating_psychic_blast", 
      "attack_value": 11, 
      "defense_power": "invincible", 
      "defense_value": 18, 
      "damage_power": "leadership", 
      "damage_value": 4
    }, 
    {
      "click_number": 3, 
      "speed_power": "running_shot", 
      "speed_value": 10, 
      "attack_power": "energy_explosion", 
      "attack_value": 11, 
      "defense_power": "impervious", 
      "defense_value": 18, 
      "damage_power": "leadership", 
      "damage_value": 4
    }, 
    {
      "click_number": 4, 
      "speed_power": "running_shot", 
      "speed_value": 10, 
      "attack_power": "energy_explosion", 
      "attack_value": 11, 
      "defense_power": "impervious", 
      "defense_value": 18, 
      "damage_power": "probability_control", 
      "damage_value": 4, 
      "starting_line": true
    }, 
    {
      "click_number": 5, 
      "speed_power": "phasing_teleport", 
      "speed_value": 10, 
      "attack_power": "energy_explosion", 
      "attack_value": 10, 
      "defense_power": "impervious", 
      "defense_value": 17, 
      "damage_power": "probability_control", 
      "damage_value": 3
    }, 
    {
      "click_number": 6, 
      "speed_power": "phasing_teleport", 
      "speed_value": 10, 
      "attack_power": "pulse_wave", 
      "attack_value": 10, 
      "defense_power": "invulnerability", 
      "defense_value": 18, 
      "damage_power": "probability_control", 
      "damage_value": 3
    }, 
    {
      "click_number": 7, 
      "speed_power": "phasing_teleport", 
      "speed_value": 10, 
      "attack_power": "pulse_wave", 
      "attack_value": 10, 
      "defense_power": "invulnerability", 
      "defense_value": 17, 
      "damage_power": "probability_control", 
      "damage_value": 3
    }, 
    {
      "click_number": 8, 
      "speed_power": "phasing_teleport", 
      "speed_value": 10, 
      "attack_power": "super_strength", 
      "attack_value": 12, 
      "defense_power": "impervious", 
      "defense_value": 17, 
      "damage_power": "empower", 
      "damage_value": 3
    }, 
    {
      "click_number": 9, 
      "speed_power": "charge", 
      "speed_value": 10, 
      "attack_power": "super_strength", 
      "attack_value": 11, 
      "defense_power": "impervious", 
      "defense_value": 17, 
      "damage_power": "empower", 
      "damage_value": 4
    }, 
    {
      "click_number": 10, 
      "speed_power": "charge", 
      "speed_value": 8, 
      "attack_power": "super_strength", 
      "attack_value": 10, 
      "defense_power": "invulnerability", 
      "defense_value": 18, 
      "damage_power": "empower", 
      "damage_value": 5
    }
  ]
}, {
  "unit_id": "tdw101", 
  "set_id": "tdw", 
  "collector_number": "101", 
  "name": "Thor", 
  "type": "character", 
  "rarity": "common", 
  "dimensions": "1x1", 
  "point_values": [
    175, 
    100
  ], 
  "team_abilities": [
    "avengers_initiative"
  ], 
  "keywords": [
    "Asgardian", 
    "Avengers", 
    "Deity", 
    "Warrior"
  ], 
  "special_powers": [
    {
      "type": "speed", 
      "name": "WHOSOEVER HOLDS THIS HAMMER...", 
      "description": "Thor can use Charge. He can use it normally, or when he is given an action to use Charge, if he moves in a direct line, he can use [im:characters] and, after actions resolve, each character occupying a square that Thor moved through is dealt 1 damage, assigned an action token, and you may place it in a square adjacent to their current position.", 
      "powers": [
        "charge"
      ]
    }, 
    {
      "type": "attack", 
      "name": "GOD OF THUNDER", 
      "description": "Thor can use Energy Explosion. When he is given a ranged combat action, you may lock his damage value and, if you do, all hit characters are also given an action token.", 
      "powers": [
        "energy_explosion"
      ]
    }
  ], 
  "unit_range": 8, 
  "targets": 1, 
  "speed_type": "wing", 
  "attack_type": "fist", 
  "defense_type": "indomitable", 
  "damage_type": "starburst", 
  "dial_size": 12, 
  "dial": [
    {
      "click_number": 1, 
      "starting_line": true, 
      "speed_power": "special", 
      "speed_value": 10, 
      "attack_power": "quake", 
      "attack_value": 11, 
      "defense_power": "impervious", 
      "defense_value": 18, 
      "damage_value": 4
    }, 
    {
      "click_number": 2, 
      "speed_power": "special", 
      "speed_value": 9, 
      "attack_power": "super_strength", 
      "attack_value": 11, 
      "defense_power": "invulnerability", 
      "defense_value": 17, 
      "damage_power": "empower", 
      "damage_value": 3
    }, 
    {
      "click_number": 3, 
      "speed_power": "special", 
      "speed_value": 9, 
      "attack_power": "super_strength", 
      "attack_value": 10, 
      "defense_power": "invulnerability", 
      "defense_value": 17, 
      "damage_power": "empower", 
      "damage_value": 3
    }, 
    {
      "click_number": 4, 
      "speed_power": "running_shot", 
      "speed_value": 8, 
      "attack_power": "special", 
      "attack_value": 10, 
      "defense_power": "impervious", 
      "defense_value": 17, 
      "damage_value": 3, 
      "starting_line": true
    }, 
    {
      "click_number": 5, 
      "speed_power": "running_shot", 
      "speed_value": 7, 
      "attack_power": "special", 
      "attack_value": 9, 
      "defense_power": "invulnerability", 
      "defense_value": 17, 
      "damage_power": "enhancement", 
      "damage_value": 3
    }, 
    {
      "click_number": 6, 
      "speed_power": "running_shot", 
      "speed_value": 8, 
      "attack_power": "special", 
      "attack_value": 9, 
      "defense_power": "invulnerability", 
      "defense_value": 16, 
      "damage_power": "exploit_weakness", 
      "damage_value": 3
    }, 
    {
      "click_number": 7, 
      "speed_power": "special", 
      "speed_value": 9, 
      "attack_power": "quake", 
      "attack_value": 9, 
      "defense_power": "toughness", 
      "defense_value": 17, 
      "damage_power": "exploit_weakness", 
      "damage_value": 2
    }, 
    {
      "click_number": 8, 
      "speed_value": 8, 
      "attack_value": 9, 
      "defense_power": "toughness", 
      "defense_value": 16, 
      "damage_power": "exploit_weakness", 
      "damage_value": 2
    }
  ]
}, {
  "unit_id": "tdw102", 
  "set_id": "tdw", 
  "collector_number": "102", 
  "name": "Malekith", 
  "type": "character", 
  "rarity": "common", 
  "dimensions": "1x1", 
  "point_values": [
    100
  ], 
  "keywords": [
    "Mystical", 
    "Ruler", 
    "Svartalfheim", 
    "Warrior"
  ], 
  "special_powers": [
    {
      "type": "trait", 
      "name": "AVERSION TO IRON", 
      "description": "When Malekith is dealt damage and the attacker rolled a d6 for Blades/Claws/Fangs for the attack, damage dealt can't be reduced below 1."
    }, 
    {
      "type": "speed", 
      "name": "AWAY FROM ME, ASGARDIAN!", 
      "description": "Malekith can use Force Blast and Sidestep.", 
      "powers": [
        "force_blast", 
        "sidestep"
      ]
    }, 
    {
      "type": "damage", 
      "name": "THE DECEIVER", 
      "description": "Malekith can use Mastermind, Shape Change, and Super Senses.", 
      "powers": [
        "mastermind", 
        "shape_change", 
        "super_senses"
      ]
    }
  ], 
  "unit_range": 6, 
  "targets": 1, 
  "speed_type": "boot", 
  "attack_type": "fist", 
  "defense_type": "shield", 
  "damage_type": "starburst", 
  "dial_size": 12, 
  "dial": [
    {
      "click_number": 1, 
      "starting_line": true, 
      "speed_power": "special", 
      "speed_value": 9, 
      "attack_power": "super_strength", 
      "attack_value": 11, 
      "defense_power": "invulnerability", 
      "defense_value": 17, 
      "damage_power": "shape_change", 
      "damage_value": 3
    }, 
    {
      "click_number": 2, 
      "speed_power": "special", 
      "speed_value": 9, 
      "attack_power": "super_strength", 
      "attack_value": 10, 
      "defense_power": "invulnerability", 
      "defense_value": 17, 
      "damage_power": "shape_change", 
      "damage_value": 3
    }, 
    {
      "click_number": 3, 
      "speed_power": "special", 
      "speed_value": 9, 
      "attack_power": "penetrating_psychic_blast", 
      "attack_value": 9, 
      "defense_power": "invulnerability", 
      "defense_value": 17, 
      "damage_power": "shape_change", 
      "damage_value": 2
    }, 
    {
      "click_number": 4, 
      "speed_power": "phasing_teleport", 
      "speed_value": 8, 
      "attack_power": "penetrating_psychic_blast", 
      "attack_value": 9, 
      "defense_power": "toughness", 
      "defense_value": 16, 
      "damage_power": "special", 
      "damage_value": 2
    }, 
    {
      "click_number": 5, 
      "speed_power": "phasing_teleport", 
      "speed_value": 8, 
      "attack_power": "penetrating_psychic_blast", 
      "attack_value": 9, 
      "defense_power": "toughness", 
      "defense_value": 15, 
      "damage_power": "special", 
      "damage_value": 2
    }, 
    {
      "click_number": 6, 
      "speed_power": "phasing_teleport", 
      "speed_value": 7, 
      "attack_power": "pulse_wave", 
      "attack_value": 10, 
      "defense_power": "toughness", 
      "defense_value": 16, 
      "damage_power": "special", 
      "damage_value": 2
    }, 
    {
      "click_number": 7, 
      "speed_power": "phasing_teleport", 
      "speed_value": 6, 
      "attack_power": "pulse_wave", 
      "attack_value": 11, 
      "defense_power": "regeneration", 
      "defense_value": 17, 
      "damage_power": "special", 
      "damage_value": 3
    }
  ]
}, {
  "unit_id": "tdw103", 
  "set_id": "tdw", 
  "collector_number": "103", 
  "name": "Sif", 
  "type": "character", 
  "rarity": "common", 
  "dimensions": "1x1", 
  "point_values": [
    75
  ], 
  "keywords": [
    "Asgardian", 
    "Deity", 
    "Warrior"
  ], 
  "improved_movement": [
    "characters"
  ], 
  "unit_range": 0, 
  "targets": 1, 
  "speed_type": "boot", 
  "attack_type": "fist", 
  "defense_type": "shield", 
  "damage_type": "starburst", 
  "dial_size": 12, 
  "dial": [
    {
      "click_number": 1, 
      "starting_line": true, 
      "speed_power": "charge", 
      "speed_value": 9, 
      "attack_power": "blades_claws_fangs", 
      "attack_value": 10, 
      "defense_power": "invulnerability", 
      "defense_value": 17, 
      "damage_value": 2
    }, 
    {
      "click_number": 2, 
      "speed_power": "charge", 
      "speed_value": 8, 
      "attack_power": "blades_claws_fangs", 
      "attack_value": 9, 
      "defense_power": "combat_reflexes", 
      "defense_value": 17, 
      "damage_value": 2
    }, 
    {
      "click_number": 3, 
      "speed_power": "flurry", 
      "speed_value": 8, 
      "attack_power": "precision_strike", 
      "attack_value": 10, 
      "defense_power": "combat_reflexes", 
      "defense_value": 16, 
      "damage_power": "battle_fury", 
      "damage_value": 2
    }, 
    {
      "click_number": 4, 
      "speed_power": "flurry", 
      "speed_value": 8, 
      "attack_power": "precision_strike", 
      "attack_value": 9, 
      "defense_power": "combat_reflexes", 
      "defense_value": 16, 
      "damage_power": "battle_fury", 
      "damage_value": 2
    }, 
    {
      "click_number": 5, 
      "speed_power": "sidestep", 
      "speed_value": 7, 
      "attack_power": "blades_claws_fangs", 
      "attack_value": 10, 
      "defense_power": "combat_reflexes", 
      "defense_value": 15, 
      "damage_power": "exploit_weakness", 
      "damage_value": 2
    }, 
    {
      "click_number": 6, 
      "speed_power": "sidestep", 
      "speed_value": 7, 
      "attack_power": "blades_claws_fangs", 
      "attack_value": 9, 
      "defense_power": "toughness", 
      "defense_value": 16, 
      "damage_power": "exploit_weakness", 
      "damage_value": 2
    }
  ]
}, {
  "unit_id": "tdw104", 
  "set_id": "tdw", 
  "collector_number": "104", 
  "name": "Loki", 
  "type": "character", 
  "rarity": "common", 
  "dimensions": "1x1", 
  "point_values": [
    100
  ], 
  "keywords": [
    "Asgardian", 
    "Deity", 
    "Mystical"
  ], 
  "special_powers": [
    {
      "type": "defense", 
      "name": "ILLUSORY DUPLICATES", 
      "description": "Loki can use Shape Change and Toughness. When he uses Shape Change and succeeds, Loki may be placed in a square of hindering terrain within 3 squares and line of fire. If the attack was a close combat attack, the attacker's action resolves immediately.", 
      "powers": [
        "shape_change", 
        "toughness"
      ]
    }
  ], 
  "unit_range": 6, 
  "targets": 1, 
  "speed_type": "boot", 
  "attack_type": "fist", 
  "defense_type": "shield", 
  "damage_type": "starburst", 
  "dial_size": 12, 
  "dial": [
    {
      "click_number": 1, 
      "starting_line": true, 
      "speed_power": "phasing_teleport", 
      "speed_value": 10, 
      "attack_value": 10, 
      "defense_power": "special", 
      "defense_value": 17, 
      "damage_power": "perplex", 
      "damage_value": 3
    }, 
    {
      "click_number": 2, 
      "speed_power": "phasing_teleport", 
      "speed_value": 10, 
      "attack_power": "penetrating_psychic_blast", 
      "attack_value": 10, 
      "defense_power": "special", 
      "defense_value": 17, 
      "damage_power": "perplex", 
      "damage_value": 2
    }, 
    {
      "click_number": 3, 
      "speed_power": "phasing_teleport", 
      "speed_value": 9, 
      "attack_power": "penetrating_psychic_blast", 
      "attack_value": 9, 
      "defense_power": "special", 
      "defense_value": 17, 
      "damage_power": "perplex", 
      "damage_value": 2
    }, 
    {
      "click_number": 4, 
      "speed_power": "stealth", 
      "speed_value": 8, 
      "attack_power": "incapacitate", 
      "attack_value": 9, 
      "defense_power": "invulnerability", 
      "defense_value": 16, 
      "damage_power": "outwit", 
      "damage_value": 2
    }, 
    {
      "click_number": 5, 
      "speed_power": "stealth", 
      "speed_value": 8, 
      "attack_power": "incapacitate", 
      "attack_value": 8, 
      "defense_power": "invulnerability", 
      "defense_value": 16, 
      "damage_power": "outwit", 
      "damage_value": 1
    }, 
    {
      "click_number": 6, 
      "speed_power": "charge", 
      "speed_value": 7, 
      "attack_power": "blades_claws_fangs", 
      "attack_value": 9, 
      "defense_value": 17, 
      "damage_power": "battle_fury", 
      "damage_value": 2
    }, 
    {
      "click_number": 7, 
      "speed_power": "charge", 
      "speed_value": 7, 
      "attack_power": "blades_claws_fangs", 
      "attack_value": 10, 
      "defense_value": 16, 
      "damage_power": "battle_fury", 
      "damage_value": 3
    }
  ]
}, {
  "unit_id": "tdw105", 
  "set_id": "tdw", 
  "collector_number": "105", 
  "name": "Dark Elf Scout", 
  "type": "character", 
  "rarity": "common", 
  "dimensions": "1x1", 
  "point_values": [
    50
  ], 
  "properties": [
    "generic"
  ], 
  "keywords": [
    "Soldier", 
    "Svartalfheim"
  ], 
  "special_powers": [
    {
      "type": "attack", 
      "name": "POWER OF THE AETHER", 
      "description": "Opposing characters hit by Dark Elf Scout's ranged combat attack can't use the Flight ability until your next turn."
    }, 
    {
      "type": "damage", 
      "name": "MINION: ASGARDIAN RECONNAISSANCE", 
      "description": "If a friendly character named Malekith is within 8 squares, Dark Elf Scout can use Enhancement.", 
      "powers": [
        "enhancement"
      ]
    }
  ], 
  "unit_range": 5, 
  "targets": 1, 
  "speed_type": "wing", 
  "attack_type": "fist", 
  "defense_type": "shield", 
  "damage_type": "starburst", 
  "dial_size": 12, 
  "dial": [
    {
      "click_number": 1, 
      "starting_line": true, 
      "speed_power": "stealth", 
      "speed_value": 8, 
      "attack_power": "special", 
      "attack_value": 9, 
      "defense_power": "super_senses", 
      "defense_value": 16, 
      "damage_power": "special", 
      "damage_value": 2
    }, 
    {
      "click_number": 2, 
      "speed_power": "stealth", 
      "speed_value": 8, 
      "attack_power": "special", 
      "attack_value": 9, 
      "defense_power": "super_senses", 
      "defense_value": 16, 
      "damage_power": "special", 
      "damage_value": 2
    }, 
    {
      "click_number": 3, 
      "speed_power": "stealth", 
      "speed_value": 7, 
      "attack_power": "incapacitate", 
      "attack_value": 9, 
      "defense_power": "super_senses", 
      "defense_value": 16, 
      "damage_power": "special", 
      "damage_value": 1
    }, 
    {
      "click_number": 4, 
      "speed_power": "earthbound_neutralized", 
      "speed_value": 6, 
      "attack_power": "incapacitate", 
      "attack_value": 8, 
      "defense_power": "willpower", 
      "defense_value": 15, 
      "damage_power": "shape_change", 
      "damage_value": 1
    }, 
    {
      "click_number": 5, 
      "speed_power": "earthbound_neutralized", 
      "speed_value": 5, 
      "attack_power": "incapacitate", 
      "attack_value": 8, 
      "defense_power": "willpower", 
      "defense_value": 15, 
      "damage_power": "shape_change", 
      "damage_value": 1
    }, 
    {
      "click_number": 6, 
      "speed_power": "earthbound_neutralized", 
      "speed_value": 5, 
      "attack_power": "incapacitate", 
      "attack_value": 8, 
      "defense_power": "willpower", 
      "defense_value": 15, 
      "damage_power": "shape_change", 
      "damage_value": 1
    }
  ]
}, {
  "unit_id": "tdw106", 
  "set_id": "tdw", 
  "collector_number": "106", 
  "name": "Kurse", 
  "type": "character", 
  "rarity": "common", 
  "dimensions": "1x1", 
  "point_values": [
    150
  ], 
  "keywords": [
    "Armor", 
    "Brute", 
    "Svartalfheim", 
    "Warrior"
  ], 
  "special_powers": [
    {
      "type": "trait", 
      "name": "UNBREAKABLE ARMOR", 
      "description": "Kurse's defense powers can't be countered."
    }, 
    {
      "type": "speed", 
      "name": "THE WILD HUNT", 
      "description": "During your first turn, choose an opposing character. Kurse can use Charge. He can chose to use it normally, or he may choose to not halve his speed value from Charge, but may then only make close combat attacks against the chosen opposing character during that action.", 
      "powers": [
        "charge"
      ]
    }
  ], 
  "unit_range": 0, 
  "targets": 1, 
  "speed_type": "boot", 
  "attack_type": "fist", 
  "defense_type": "indomitable", 
  "damage_type": "starburst", 
  "dial_size": 12, 
  "dial": [
    {
      "click_number": 1, 
      "starting_line": true, 
      "speed_power": "special", 
      "speed_value": 8, 
      "attack_power": "super_strength", 
      "attack_value": 11, 
      "defense_power": "invincible", 
      "defense_value": 17, 
      "damage_value": 4
    }, 
    {
      "click_number": 2, 
      "speed_power": "special", 
      "speed_value": 7, 
      "attack_power": "super_strength", 
      "attack_value": 10, 
      "defense_power": "invincible", 
      "defense_value": 17, 
      "damage_value": 4
    }, 
    {
      "click_number": 3, 
      "speed_power": "special", 
      "speed_value": 7, 
      "attack_power": "super_strength", 
      "attack_value": 10, 
      "defense_power": "impervious", 
      "defense_value": 17, 
      "damage_value": 3
    }, 
    {
      "click_number": 4, 
      "speed_power": "charge", 
      "speed_value": 7, 
      "attack_power": "super_strength", 
      "attack_value": 10, 
      "defense_power": "impervious", 
      "defense_value": 17, 
      "damage_value": 3
    }, 
    {
      "click_number": 5, 
      "speed_power": "charge", 
      "speed_value": 6, 
      "attack_power": "super_strength", 
      "attack_value": 9, 
      "defense_power": "invulnerability", 
      "defense_value": 17, 
      "damage_value": 3
    }, 
    {
      "click_number": 6, 
      "speed_power": "charge", 
      "speed_value": 6, 
      "attack_power": "super_strength", 
      "attack_value": 9, 
      "defense_power": "invulnerability", 
      "defense_value": 17, 
      "damage_value": 3
    }, 
    {
      "click_number": 7, 
      "speed_value": 6, 
      "attack_power": "super_strength", 
      "attack_value": 9, 
      "defense_power": "invulnerability", 
      "defense_value": 16, 
      "damage_value": 3
    }, 
    {
      "click_number": 8, 
      "speed_value": 6, 
      "attack_power": "super_strength", 
      "attack_value": 9, 
      "defense_power": "invulnerability", 
      "defense_value": 16, 
      "damage_value": 2
    }
  ]
}, {
  "unit_id": "tdwH001", 
  "set_id": "tdw", 
  "collector_number": "H001", 
  "name": "Einherjar Captain", 
  "type": "bystander", 
  "rarity": "common", 
  "dimensions": "1x1", 
  "point_values": [
    20
  ], 
  "special_powers": [
    {
      "type": "damage", 
      "name": "HORDE: TO ARMS ASGARD!", 
      "description": "When stacked, Einherjar Captain can use Leadership. When (M), Einherjar Captain can use Empower.", 
      "powers": [
        "leadership", 
        "empower"
      ]
    }
  ], 
  "bystander_type": "horde", 
  "horde_stack_max": 3, 
  "unit_range": 3, 
  "targets": 1, 
  "speed_type": "boot", 
  "attack_type": "fist", 
  "defense_type": "shield", 
  "damage_type": "starburst", 
  "dial_size": 1, 
  "dial": [
    {
      "click_number": 1, 
      "starting_line": true, 
      "speed_value": 7, 
      "attack_power": "precision_strike", 
      "attack_value": 10, 
      "defense_power": "toughness", 
      "defense_value": 17, 
      "damage_power": "special", 
      "damage_value": 2
    }
  ]
}, {
  "unit_id": "tdwH002", 
  "set_id": "tdw", 
  "collector_number": "H002", 
  "name": "Einherjar Lieutenant", 
  "type": "bystander", 
  "rarity": "common", 
  "dimensions": "1x1", 
  "point_values": [
    15
  ], 
  "special_powers": [
    {
      "type": "damage", 
      "name": "HORDE: MARCH!", 
      "description": "When stacked, other friendly characters whose name contains the word Einherjar and are adjacent to Einherjar Lieutenant at the beginning of the turn modify their speed value by +2 this turn."
    }
  ], 
  "bystander_type": "horde", 
  "horde_stack_max": 3, 
  "unit_range": 4, 
  "targets": 1, 
  "speed_type": "boot", 
  "attack_type": "fist", 
  "defense_type": "shield", 
  "damage_type": "starburst", 
  "dial_size": 1, 
  "dial": [
    {
      "click_number": 1, 
      "starting_line": true, 
      "speed_power": "sidestep", 
      "speed_value": 6, 
      "attack_value": 10, 
      "defense_power": "combat_reflexes", 
      "defense_value": 16, 
      "damage_power": "special", 
      "damage_value": 2
    }
  ]
}, {
  "unit_id": "tdwH003", 
  "set_id": "tdw", 
  "collector_number": "H003", 
  "name": "Einherjar Soldier", 
  "type": "bystander", 
  "rarity": "common", 
  "dimensions": "1x1", 
  "point_values": [
    15
  ], 
  "special_powers": [
    {
      "type": "damage", 
      "name": "HORDE: STAND TOGETHER", 
      "description": "When stacked, at the beginning of your turn, roll a d6. If that roll is equal to or less than (S), Einherjar Soldier can use Flurry. When (M), Einherjar Soldier can use Combat Reflexes.", 
      "powers": [
        "flurry", 
        "combat_reflexes"
      ]
    }
  ], 
  "bystander_type": "horde", 
  "horde_stack_max": 4, 
  "unit_range": 4, 
  "targets": 1, 
  "speed_type": "boot", 
  "attack_type": "fist", 
  "defense_type": "shield", 
  "damage_type": "starburst", 
  "dial_size": 1, 
  "dial": [
    {
      "click_number": 1, 
      "starting_line": true, 
      "speed_value": 7, 
      "attack_value": 10, 
      "defense_power": "toughness", 
      "defense_value": 15, 
      "damage_power": "special", 
      "damage_value": 2
    }
  ]
}, {
  "unit_id": "tdwH004", 
  "set_id": "tdw", 
  "collector_number": "H004", 
  "name": "Einherjar Trainee", 
  "type": "bystander", 
  "rarity": "common", 
  "dimensions": "1x1", 
  "point_values": [
    10
  ], 
  "special_powers": [
    {
      "type": "damage", 
      "name": "HORDE: FOLLOWING ORDERS", 
      "description": "When (M) and within 8 squares of a character named Einherjar Captain or Einherjar Lieutenant, Einherjar Trainee may be given a close combat action as a free action."
    }
  ], 
  "bystander_type": "horde", 
  "horde_stack_max": 6, 
  "unit_range": 0, 
  "targets": 1, 
  "speed_type": "boot", 
  "attack_type": "fist", 
  "defense_type": "shield", 
  "damage_type": "starburst", 
  "dial_size": 1, 
  "dial": [
    {
      "click_number": 1, 
      "starting_line": true, 
      "speed_value": 6, 
      "attack_power": "incapacitate", 
      "attack_value": 9, 
      "defense_value": 16, 
      "damage_power": "special", 
      "damage_value": 1
    }
  ]
}, {
  "unit_id": "tdwH005", 
  "set_id": "tdw", 
  "collector_number": "H005", 
  "name": "Dark Elf Warrior", 
  "type": "bystander", 
  "rarity": "common", 
  "dimensions": "1x1", 
  "point_values": [
    20
  ], 
  "special_powers": [
    {
      "type": "damage", 
      "name": "HORDE: PUSH BACK THE LINE", 
      "description": "When stacked and using Charge, characters that take damage are knocked back (S) squares."
    }
  ], 
  "bystander_type": "horde", 
  "horde_stack_max": 3, 
  "unit_range": 0, 
  "targets": 1, 
  "speed_type": "boot", 
  "attack_type": "fist", 
  "defense_type": "shield", 
  "damage_type": "starburst", 
  "dial_size": 1, 
  "dial": [
    {
      "click_number": 1, 
      "starting_line": true, 
      "speed_power": "charge", 
      "speed_value": 7, 
      "attack_value": 9, 
      "defense_power": "toughness", 
      "defense_value": 17, 
      "damage_power": "special", 
      "damage_value": 2
    }
  ]
}, {
  "unit_id": "tdwH006", 
  "set_id": "tdw", 
  "collector_number": "H006", 
  "name": "Dark Elf Scout", 
  "type": "bystander", 
  "rarity": "common", 
  "dimensions": "1x1", 
  "point_values": [
    15
  ], 
  "special_powers": [
    {
      "type": "damage", 
      "name": "HORDE: RECONNAISANCE", 
      "description": "When (M), opposing characters within 3 squares can't use Stealth."
    }
  ], 
  "bystander_type": "horde", 
  "horde_stack_max": 3, 
  "unit_range": 2, 
  "targets": 1, 
  "speed_type": "boot", 
  "attack_type": "fist", 
  "defense_type": "shield", 
  "damage_type": "starburst", 
  "dial_size": 1, 
  "dial": [
    {
      "click_number": 1, 
      "starting_line": true, 
      "speed_power": "stealth", 
      "speed_value": 7, 
      "attack_value": 9, 
      "defense_power": "combat_reflexes", 
      "defense_value": 15, 
      "damage_power": "special", 
      "damage_value": 2
    }
  ]
}, {
  "unit_id": "tdwH007", 
  "set_id": "tdw", 
  "collector_number": "H007", 
  "name": "Dark Elf Soldier", 
  "type": "bystander", 
  "rarity": "common", 
  "dimensions": "1x1", 
  "point_values": [
    15
  ], 
  "special_powers": [
    {
      "type": "damage", 
      "name": "HORDE: OVERWHELM", 
      "description": "When stacked, at the beginning of the turn roll a d6. If the result is equal to or less than (S), modify Dark Elf Soldier's attack and damage values by +1."
    }
  ], 
  "bystander_type": "horde", 
  "horde_stack_max": 4, 
  "unit_range": 4, 
  "targets": 1, 
  "speed_type": "boot", 
  "attack_type": "fist", 
  "defense_type": "shield", 
  "damage_type": "starburst", 
  "dial_size": 1, 
  "dial": [
    {
      "click_number": 1, 
      "starting_line": true, 
      "speed_power": "plasticity", 
      "speed_value": 6, 
      "attack_power": "quake", 
      "attack_value": 9, 
      "defense_value": 16, 
      "damage_power": "special", 
      "damage_value": 1
    }
  ]
}, {
  "unit_id": "tdwH008", 
  "set_id": "tdw", 
  "collector_number": "H008", 
  "name": "Dark Elf", 
  "type": "bystander", 
  "rarity": "common", 
  "dimensions": "1x1", 
  "point_values": [
    10
  ], 
  "special_powers": [
    {
      "type": "damage", 
      "name": "HORDE: STRENGTH IN NUMBERS", 
      "description": "When stacked, Dark Elf can use Empower. When (M), close combat attacks deal penetrating damage.", 
      "powers": [
        "empower"
      ]
    }
  ], 
  "bystander_type": "horde", 
  "horde_stack_max": 6, 
  "unit_range": 2, 
  "targets": 1, 
  "speed_type": "boot", 
  "attack_type": "fist", 
  "defense_type": "shield", 
  "damage_type": "starburst", 
  "dial_size": 1, 
  "dial": [
    {
      "click_number": 1, 
      "starting_line": true, 
      "speed_power": "flurry", 
      "speed_value": 6, 
      "attack_power": "quake", 
      "attack_value": 8, 
      "defense_value": 15, 
      "damage_power": "special", 
      "damage_value": 1
    }
  ]
}, {
  "unit_id": "tdwM001", 
  "set_id": "tdw", 
  "collector_number": "M001", 
  "name": "Svartalfheim", 
  "type": "map", 
  "dimensions": "16x24",
  "map_type": "outdoor",
  "map_url": "https://hcmaps.net/maps/tdw/svartalfheim.json"
}, {
  "unit_id": "tdwM002", 
  "set_id": "tdw", 
  "collector_number": "M002", 
  "name": "Royal Naval Academy", 
  "type": "map", 
  "dimensions": "16x24",
  "map_type": "outdoor",
  "special_powers": [
    {
      "name": "Interdimensional Portal", 
      "description": "Orange squares are Portal squares. Portal squares are hindering terrain. For other exciting scenarioes, check the scenario sheet included in this starter!"
    }
  ], 
  "map_url": "https://hcmaps.net/maps/tdw/royal_naval_academy.json"
}, {
  "unit_id": "tdwM003", 
  "set_id": "tdw", 
  "collector_number": "M003", 
  "name": "Svartalfheim", 
  "type": "map", 
  "dimensions": "16x6",
  "map_type": "outdoor",
  "map_url": "https://hcmaps.net/maps/tdw/svartalfheim_minigame.json"
}]